README.md
setup.py
pycaboose/__init__.py
pycaboose/database.py
pycaboose/marshal.py
pycaboose/tailwriter.py
pycaboose/value.py
pycaboose.egg-info/PKG-INFO
pycaboose.egg-info/SOURCES.txt
pycaboose.egg-info/dependency_links.txt
pycaboose.egg-info/top_level.txt
test/test_db.py
test/test_marshal.py
test/test_value.py