Metadata-Version: 2.1
Name: pycaboose
Version: 1.1.1
Summary: A python library for persisting data within a script.
Home-page: https://github.com/JohnathonNow/pycaboose
Author: John Westhoff
Author-email: johnjwesthoff@gmail.com
License: UNKNOWN
Platform: UNKNOWN
